{
  "degraded_product_count": 85,
  "generated_at": "2026-04-28T14:45:09.322933+00:00",
  "hidden_product_count": 0,
  "live_product_count": 493,
  "omitted_degraded_product_count": 0,
  "product_count": 578,
  "publish_quality_reasons": [],
  "publish_quality_status": "passed",
  "service_count": 9,
  "snapshot_hash": "6d9dc2a2287d8b7c4d8a94b5fdf037606725c7d98c35e1c9973993498d7ca791",
  "source_site_count": 56,
  "sync_finished_at": "2026-04-28T14:45:02.256701+00:00",
  "sync_run_id": "602b8e9383ca0a60",
  "sync_started_at": "2026-04-28T14:42:40.475217+00:00"
}