{
  "abnormal_site_count": 3,
  "attempted_site_count": 42,
  "counts_by_status": {
    "empty": 4,
    "error": 3,
    "healthy": 35
  },
  "generated_at": "2026-04-24T17:02:46.687154+00:00",
  "site_count": 42,
  "sites": [
    {
      "active_product_count": 12,
      "affects_publish": false,
      "attempted_in_run": true,
      "base_url": "https://www.holy-card.com",
      "is_enabled": true,
      "last_error_at": null,
      "last_error_message": null,
      "last_success_at": "2026-04-24T16:55:53.038120",
      "name": "Holy Card",
      "products_seen": 12,
      "public_product_count": 12,
      "run_data_status": "latest",
      "run_sync_status": "synced",
      "site_key": "holy_card",
      "status": "healthy"
    },
    {
      "active_product_count": 11,
      "affects_publish": false,
      "attempted_in_run": true,
      "base_url": "https://go365-card.com",
      "is_enabled": true,
      "last_error_at": null,
      "last_error_message": null,
      "last_success_at": "2026-04-24T16:55:48.096960",
      "name": "Go365 Card",
      "products_seen": 11,
      "public_product_count": 11,
      "run_data_status": "latest",
      "run_sync_status": "synced",
      "site_key": "go365",
      "status": "healthy"
    },
    {
      "active_product_count": 16,
      "affects_publish": true,
      "attempted_in_run": true,
      "base_url": "https://fk.accgood.com",
      "is_enabled": true,
      "last_error_at": "2026-04-24T16:57:14.719131",
      "last_error_message": "timed out after 90s",
      "last_success_at": "2026-04-24T16:11:17.195497",
      "name": "AccGood",
      "products_seen": null,
      "public_product_count": 16,
      "run_data_status": "stale_snapshot",
      "run_sync_status": "timeout",
      "site_key": "accgood",
      "status": "error"
    },
    {
      "active_product_count": 12,
      "affects_publish": false,
      "attempted_in_run": true,
      "base_url": "https://pay.qxvx.cn/shop/JYKGUAEK",
      "is_enabled": true,
      "last_error_at": null,
      "last_error_message": null,
      "last_success_at": "2026-04-24T16:56:27.521773",
      "name": "QXVX JYKGUAEK",
      "products_seen": 12,
      "public_product_count": 12,
      "run_data_status": "latest",
      "run_sync_status": "synced",
      "site_key": "qxvx",
      "status": "healthy"
    },
    {
      "active_product_count": 18,
      "affects_publish": false,
      "attempted_in_run": true,
      "base_url": "https://nikoers.com",
      "is_enabled": true,
      "last_error_at": null,
      "last_error_message": null,
      "last_success_at": "2026-04-24T16:56:05.993663",
      "name": "Niko Card",
      "products_seen": 18,
      "public_product_count": 18,
      "run_data_status": "latest",
      "run_sync_status": "synced",
      "site_key": "niko_card",
      "status": "healthy"
    },
    {
      "active_product_count": 10,
      "affects_publish": false,
      "attempted_in_run": true,
      "base_url": "https://traders.indevs.in",
      "is_enabled": true,
      "last_error_at": null,
      "last_error_message": null,
      "last_success_at": "2026-04-24T16:56:17.432999",
      "name": "Traders Indevs",
      "products_seen": 10,
      "public_product_count": 10,
      "run_data_status": "latest",
      "run_sync_status": "synced",
      "site_key": "traders_indevs",
      "status": "healthy"
    },
    {
      "active_product_count": 21,
      "affects_publish": false,
      "attempted_in_run": true,
      "base_url": "https://pay.ldxp.cn/shop/gugu",
      "is_enabled": true,
      "last_error_at": null,
      "last_error_message": null,
      "last_success_at": "2026-04-24T16:56:47.555322",
      "name": "LDXP Gugu",
      "products_seen": 21,
      "public_product_count": 21,
      "run_data_status": "latest",
      "run_sync_status": "synced",
      "site_key": "ldxp_gugu",
      "status": "healthy"
    },
    {
      "active_product_count": 13,
      "affects_publish": false,
      "attempted_in_run": true,
      "base_url": "https://pay.qxvx.cn/shop/AI66888",
      "is_enabled": true,
      "last_error_at": null,
      "last_error_message": null,
      "last_success_at": "2026-04-24T16:56:40.406289",
      "name": "QXVX AI66888",
      "products_seen": 13,
      "public_product_count": 13,
      "run_data_status": "latest",
      "run_sync_status": "synced",
      "site_key": "qxvx_ai66888",
      "status": "healthy"
    },
    {
      "active_product_count": 1,
      "affects_publish": false,
      "attempted_in_run": true,
      "base_url": "https://pay.ldxp.cn/shop/PY0LZKD2",
      "is_enabled": true,
      "last_error_at": null,
      "last_error_message": null,
      "last_success_at": "2026-04-24T16:57:05.153705",
      "name": "LDXP PY0LZKD2",
      "products_seen": 1,
      "public_product_count": 1,
      "run_data_status": "latest",
      "run_sync_status": "synced",
      "site_key": "ldxp_py0lzkd2",
      "status": "healthy"
    },
    {
      "active_product_count": 0,
      "affects_publish": false,
      "attempted_in_run": true,
      "base_url": "https://pay.ldxp.cn/shop/sam_altman",
      "is_enabled": true,
      "last_error_at": null,
      "last_error_message": null,
      "last_success_at": "2026-04-24T16:57:08.725988",
      "name": "LDXP Sam Altman",
      "products_seen": 0,
      "public_product_count": 0,
      "run_data_status": "empty_latest",
      "run_sync_status": "synced_empty",
      "site_key": "ldxp_sam_altman",
      "status": "empty"
    },
    {
      "active_product_count": 1,
      "affects_publish": false,
      "attempted_in_run": true,
      "base_url": "https://pay.ldxp.cn/shop/66ai",
      "is_enabled": true,
      "last_error_at": null,
      "last_error_message": null,
      "last_success_at": "2026-04-24T16:57:26.835399",
      "name": "LDXP 66AI",
      "products_seen": 1,
      "public_product_count": 1,
      "run_data_status": "latest",
      "run_sync_status": "synced",
      "site_key": "ldxp_66ai",
      "status": "healthy"
    },
    {
      "active_product_count": 44,
      "affects_publish": true,
      "attempted_in_run": true,
      "base_url": "https://www.zhanghao66.com",
      "is_enabled": true,
      "last_error_at": "2026-04-24T16:58:41.920431",
      "last_error_message": "timed out after 90s",
      "last_success_at": "2026-04-24T16:11:27.167863",
      "name": "Zhanghao66",
      "products_seen": null,
      "public_product_count": 44,
      "run_data_status": "stale_snapshot",
      "run_sync_status": "timeout",
      "site_key": "zhanghao66",
      "status": "error"
    },
    {
      "active_product_count": 0,
      "affects_publish": false,
      "attempted_in_run": true,
      "base_url": "https://pay.ldxp.cn/shop/jsonplus/iu0xjh",
      "is_enabled": true,
      "last_error_at": null,
      "last_error_message": null,
      "last_success_at": "2026-04-24T16:57:36.011346",
      "name": "LDXP JsonPlus IU0XJH",
      "products_seen": 0,
      "public_product_count": 0,
      "run_data_status": "empty_latest",
      "run_sync_status": "synced_empty",
      "site_key": "ldxp_jsonplus_iu0xjh",
      "status": "empty"
    },
    {
      "active_product_count": 6,
      "affects_publish": false,
      "attempted_in_run": true,
      "base_url": "https://pay.ldxp.cn/shop/AP9UM4KD",
      "is_enabled": true,
      "last_error_at": null,
      "last_error_message": null,
      "last_success_at": "2026-04-24T16:57:49.682227",
      "name": "LDXP AP9UM4KD",
      "products_seen": 6,
      "public_product_count": 6,
      "run_data_status": "latest",
      "run_sync_status": "synced",
      "site_key": "ldxp_ap9um4kd",
      "status": "healthy"
    },
    {
      "active_product_count": 1,
      "affects_publish": false,
      "attempted_in_run": true,
      "base_url": "https://pay.ldxp.cn/shop/WYY0418",
      "is_enabled": true,
      "last_error_at": null,
      "last_error_message": null,
      "last_success_at": "2026-04-24T16:57:58.871052",
      "name": "LDXP WYY0418",
      "products_seen": 1,
      "public_product_count": 1,
      "run_data_status": "latest",
      "run_sync_status": "synced",
      "site_key": "ldxp_wyy0418",
      "status": "healthy"
    },
    {
      "active_product_count": 0,
      "affects_publish": false,
      "attempted_in_run": true,
      "base_url": "https://pay.ldxp.cn/shop/NOAI",
      "is_enabled": true,
      "last_error_at": null,
      "last_error_message": null,
      "last_success_at": "2026-04-24T16:58:11.133135",
      "name": "LDXP NOAI",
      "products_seen": 0,
      "public_product_count": 0,
      "run_data_status": "empty_latest",
      "run_sync_status": "synced_empty",
      "site_key": "ldxp_noai",
      "status": "empty"
    },
    {
      "active_product_count": 2,
      "affects_publish": false,
      "attempted_in_run": true,
      "base_url": "https://pay.ldxp.cn/shop/110Y9VXG",
      "is_enabled": true,
      "last_error_at": null,
      "last_error_message": null,
      "last_success_at": "2026-04-24T16:58:17.523387",
      "name": "LDXP 110Y9VXG",
      "products_seen": 2,
      "public_product_count": 2,
      "run_data_status": "latest",
      "run_sync_status": "synced",
      "site_key": "ldxp_110y9vxg",
      "status": "healthy"
    },
    {
      "active_product_count": 6,
      "affects_publish": false,
      "attempted_in_run": true,
      "base_url": "https://pay.ldxp.cn/shop/IXEN9TKS",
      "is_enabled": true,
      "last_error_at": null,
      "last_error_message": null,
      "last_success_at": "2026-04-24T16:58:48.297564",
      "name": "LDXP IXEN9TKS",
      "products_seen": 6,
      "public_product_count": 6,
      "run_data_status": "latest",
      "run_sync_status": "synced",
      "site_key": "ldxp_ixen9tks",
      "status": "healthy"
    },
    {
      "active_product_count": 8,
      "affects_publish": false,
      "attempted_in_run": true,
      "base_url": "https://pay.ldxp.cn/shop/BT5B4JQA",
      "is_enabled": true,
      "last_error_at": null,
      "last_error_message": null,
      "last_success_at": "2026-04-24T16:58:33.220896",
      "name": "LDXP BT5B4JQA",
      "products_seen": 8,
      "public_product_count": 8,
      "run_data_status": "latest",
      "run_sync_status": "synced",
      "site_key": "ldxp_bt5b4jqa",
      "status": "healthy"
    },
    {
      "active_product_count": 1,
      "affects_publish": false,
      "attempted_in_run": true,
      "base_url": "https://gmail6868.com",
      "is_enabled": true,
      "last_error_at": null,
      "last_error_message": null,
      "last_success_at": "2026-04-24T16:58:38.893385",
      "name": "Gmail6868",
      "products_seen": 1,
      "public_product_count": 1,
      "run_data_status": "latest",
      "run_sync_status": "synced",
      "site_key": "gmail6868",
      "status": "healthy"
    },
    {
      "active_product_count": 16,
      "affects_publish": false,
      "attempted_in_run": true,
      "base_url": "https://pay.ldxp.cn/shop/8YKCHEQ8",
      "is_enabled": true,
      "last_error_at": null,
      "last_error_message": null,
      "last_success_at": "2026-04-24T16:59:14.733049",
      "name": "LDXP 8YKCHEQ8",
      "products_seen": 16,
      "public_product_count": 16,
      "run_data_status": "latest",
      "run_sync_status": "synced",
      "site_key": "ldxp_8ykcheq8",
      "status": "healthy"
    },
    {
      "active_product_count": 35,
      "affects_publish": false,
      "attempted_in_run": true,
      "base_url": "https://pay.ldxp.cn/shop/jinyao",
      "is_enabled": true,
      "last_error_at": null,
      "last_error_message": null,
      "last_success_at": "2026-04-24T16:59:27.449948",
      "name": "LDXP Jinyao",
      "products_seen": 35,
      "public_product_count": 35,
      "run_data_status": "latest",
      "run_sync_status": "synced",
      "site_key": "ldxp_jinyao",
      "status": "healthy"
    },
    {
      "active_product_count": 0,
      "affects_publish": false,
      "attempted_in_run": true,
      "base_url": "https://aifk.opensora.de",
      "is_enabled": true,
      "last_error_at": null,
      "last_error_message": null,
      "last_success_at": "2026-04-24T16:58:53.593831",
      "name": "AIFK OpenSora",
      "products_seen": 0,
      "public_product_count": 0,
      "run_data_status": "empty_latest",
      "run_sync_status": "synced_empty",
      "site_key": "aifk_opensora",
      "status": "empty"
    },
    {
      "active_product_count": 3,
      "affects_publish": false,
      "attempted_in_run": true,
      "base_url": "https://www.aibjz.com",
      "is_enabled": true,
      "last_error_at": null,
      "last_error_message": null,
      "last_success_at": "2026-04-24T16:58:59.786944",
      "name": "AIBJZ",
      "products_seen": 3,
      "public_product_count": 3,
      "run_data_status": "latest",
      "run_sync_status": "synced",
      "site_key": "aibjz",
      "status": "healthy"
    },
    {
      "active_product_count": 5,
      "affects_publish": false,
      "attempted_in_run": true,
      "base_url": "https://pay.ldxp.cn/shop/WR09NYJN",
      "is_enabled": true,
      "last_error_at": null,
      "last_error_message": null,
      "last_success_at": "2026-04-24T16:59:38.747207",
      "name": "LDXP WR09NYJN",
      "products_seen": 5,
      "public_product_count": 5,
      "run_data_status": "latest",
      "run_sync_status": "synced",
      "site_key": "ldxp_wr09nyjn",
      "status": "healthy"
    },
    {
      "active_product_count": 5,
      "affects_publish": false,
      "attempted_in_run": true,
      "base_url": "https://pay.ldxp.cn/shop/I1R9BRL1",
      "is_enabled": true,
      "last_error_at": null,
      "last_error_message": null,
      "last_success_at": "2026-04-24T16:59:55.121839",
      "name": "LDXP I1R9BRL1",
      "products_seen": 5,
      "public_product_count": 5,
      "run_data_status": "latest",
      "run_sync_status": "synced",
      "site_key": "ldxp_i1r9brl1",
      "status": "healthy"
    },
    {
      "active_product_count": 12,
      "affects_publish": false,
      "attempted_in_run": true,
      "base_url": "https://pay.ldxp.cn/shop/WOXP888",
      "is_enabled": true,
      "last_error_at": null,
      "last_error_message": null,
      "last_success_at": "2026-04-24T17:00:11.972277",
      "name": "LDXP WOXP888",
      "products_seen": 12,
      "public_product_count": 12,
      "run_data_status": "latest",
      "run_sync_status": "synced",
      "site_key": "ldxp_woxp888",
      "status": "healthy"
    },
    {
      "active_product_count": 6,
      "affects_publish": true,
      "attempted_in_run": true,
      "base_url": "https://ferrigpt.asia",
      "is_enabled": true,
      "last_error_at": "2026-04-24T16:59:42.620743",
      "last_error_message": "[SSL: SSLV3_ALERT_HANDSHAKE_FAILURE] sslv3 alert handshake failure (_ssl.c:1010)",
      "last_success_at": "2026-04-18T04:11:43.523434",
      "name": "FerriGPT",
      "products_seen": null,
      "public_product_count": 0,
      "run_data_status": "stale_snapshot",
      "run_sync_status": "transport_error",
      "site_key": "ferrigpt",
      "status": "error"
    },
    {
      "active_product_count": 3,
      "affects_publish": false,
      "attempted_in_run": true,
      "base_url": "https://kk.gptchong.com",
      "is_enabled": true,
      "last_error_at": null,
      "last_error_message": null,
      "last_success_at": "2026-04-24T16:59:50.166874",
      "name": "KK GPTChong",
      "products_seen": 3,
      "public_product_count": 3,
      "run_data_status": "latest",
      "run_sync_status": "synced",
      "site_key": "kk_gptchong",
      "status": "healthy"
    },
    {
      "active_product_count": 10,
      "affects_publish": false,
      "attempted_in_run": true,
      "base_url": "https://pay.ldxp.cn/shop/ppm",
      "is_enabled": true,
      "last_error_at": null,
      "last_error_message": null,
      "last_success_at": "2026-04-24T17:00:25.962790",
      "name": "LDXP PPM",
      "products_seen": 10,
      "public_product_count": 10,
      "run_data_status": "latest",
      "run_sync_status": "synced",
      "site_key": "ldxp_ppm",
      "status": "healthy"
    },
    {
      "active_product_count": 3,
      "affects_publish": false,
      "attempted_in_run": true,
      "base_url": "https://pay.ldxp.cn/shop/aicc888",
      "is_enabled": true,
      "last_error_at": null,
      "last_error_message": null,
      "last_success_at": "2026-04-24T17:00:37.123039",
      "name": "LDXP AICC888",
      "products_seen": 3,
      "public_product_count": 3,
      "run_data_status": "latest",
      "run_sync_status": "synced",
      "site_key": "ldxp_aicc888",
      "status": "healthy"
    },
    {
      "active_product_count": 17,
      "affects_publish": false,
      "attempted_in_run": true,
      "base_url": "https://pay.ldxp.cn/shop/MEDDEX4V",
      "is_enabled": true,
      "last_error_at": null,
      "last_error_message": null,
      "last_success_at": "2026-04-24T17:00:52.599592",
      "name": "LDXP MEDDEX4V",
      "products_seen": 17,
      "public_product_count": 17,
      "run_data_status": "latest",
      "run_sync_status": "synced",
      "site_key": "ldxp_meddex4v",
      "status": "healthy"
    },
    {
      "active_product_count": 2,
      "affects_publish": false,
      "attempted_in_run": true,
      "base_url": "https://pay.ldxp.cn/shop/MYIAKTYT",
      "is_enabled": true,
      "last_error_at": null,
      "last_error_message": null,
      "last_success_at": "2026-04-24T17:01:00.935166",
      "name": "LDXP MYIAKTYT",
      "products_seen": 2,
      "public_product_count": 2,
      "run_data_status": "latest",
      "run_sync_status": "synced",
      "site_key": "ldxp_myiaktyt",
      "status": "healthy"
    },
    {
      "active_product_count": 6,
      "affects_publish": false,
      "attempted_in_run": true,
      "base_url": "https://pay.ldxp.cn/shop/GDU5JC5Q",
      "is_enabled": true,
      "last_error_at": null,
      "last_error_message": null,
      "last_success_at": "2026-04-24T17:01:16.476896",
      "name": "LDXP GDU5JC5Q",
      "products_seen": 6,
      "public_product_count": 6,
      "run_data_status": "latest",
      "run_sync_status": "synced",
      "site_key": "ldxp_gdu5jc5q",
      "status": "healthy"
    },
    {
      "active_product_count": 3,
      "affects_publish": false,
      "attempted_in_run": true,
      "base_url": "https://pay.ldxp.cn/shop/pikachutoken",
      "is_enabled": true,
      "last_error_at": null,
      "last_error_message": null,
      "last_success_at": "2026-04-24T17:01:27.694072",
      "name": "LDXP PikachuToken",
      "products_seen": 3,
      "public_product_count": 3,
      "run_data_status": "latest",
      "run_sync_status": "synced",
      "site_key": "ldxp_pikachutoken",
      "status": "healthy"
    },
    {
      "active_product_count": 26,
      "affects_publish": false,
      "attempted_in_run": true,
      "base_url": "https://pay.ldxp.cn/shop/Q0GWJ4YV",
      "is_enabled": true,
      "last_error_at": null,
      "last_error_message": null,
      "last_success_at": "2026-04-24T17:01:48.778480",
      "name": "LDXP Q0GWJ4YV",
      "products_seen": 26,
      "public_product_count": 26,
      "run_data_status": "latest",
      "run_sync_status": "synced",
      "site_key": "ldxp_q0gwj4yv",
      "status": "healthy"
    },
    {
      "active_product_count": 1,
      "affects_publish": false,
      "attempted_in_run": true,
      "base_url": "https://pay.ldxp.cn/shop/ai67",
      "is_enabled": true,
      "last_error_at": null,
      "last_error_message": null,
      "last_success_at": "2026-04-24T17:01:51.464901",
      "name": "LDXP AI67",
      "products_seen": 1,
      "public_product_count": 1,
      "run_data_status": "latest",
      "run_sync_status": "synced",
      "site_key": "ldxp_ai67",
      "status": "healthy"
    },
    {
      "active_product_count": 11,
      "affects_publish": false,
      "attempted_in_run": true,
      "base_url": "https://pay.ldxp.cn/shop/CodexBro",
      "is_enabled": true,
      "last_error_at": null,
      "last_error_message": null,
      "last_success_at": "2026-04-24T17:02:17.739650",
      "name": "LDXP CodexBro",
      "products_seen": 11,
      "public_product_count": 11,
      "run_data_status": "latest",
      "run_sync_status": "synced",
      "site_key": "ldxp_codexbro",
      "status": "healthy"
    },
    {
      "active_product_count": 3,
      "affects_publish": false,
      "attempted_in_run": true,
      "base_url": "https://pay.ldxp.cn/shop/nyyy03",
      "is_enabled": true,
      "last_error_at": null,
      "last_error_message": null,
      "last_success_at": "2026-04-24T17:02:13.193619",
      "name": "LDXP NYYY03",
      "products_seen": 3,
      "public_product_count": 3,
      "run_data_status": "latest",
      "run_sync_status": "synced",
      "site_key": "ldxp_nyyy03",
      "status": "healthy"
    },
    {
      "active_product_count": 9,
      "affects_publish": false,
      "attempted_in_run": true,
      "base_url": "https://pay.ldxp.cn/shop/TSW7DIEI",
      "is_enabled": true,
      "last_error_at": null,
      "last_error_message": null,
      "last_success_at": "2026-04-24T17:02:34.424072",
      "name": "LDXP TSW7DIEI",
      "products_seen": 9,
      "public_product_count": 9,
      "run_data_status": "latest",
      "run_sync_status": "synced",
      "site_key": "ldxp_tsw7diei",
      "status": "healthy"
    },
    {
      "active_product_count": 5,
      "affects_publish": false,
      "attempted_in_run": true,
      "base_url": "https://miku88.com",
      "is_enabled": true,
      "last_error_at": null,
      "last_error_message": null,
      "last_success_at": "2026-04-24T17:02:22.779736",
      "name": "Miku88",
      "products_seen": 5,
      "public_product_count": 5,
      "run_data_status": "latest",
      "run_sync_status": "synced",
      "site_key": "miku88",
      "status": "healthy"
    },
    {
      "active_product_count": 1,
      "affects_publish": false,
      "attempted_in_run": true,
      "base_url": "https://ifaka.app",
      "is_enabled": true,
      "last_error_at": null,
      "last_error_message": null,
      "last_success_at": "2026-04-24T17:02:21.964572",
      "name": "Ifaka",
      "products_seen": 1,
      "public_product_count": 1,
      "run_data_status": "latest",
      "run_sync_status": "synced",
      "site_key": "ifaka",
      "status": "healthy"
    }
  ],
  "sync_finished_at": "2026-04-24T17:02:34.428083+00:00",
  "sync_run_id": "674d16bfd5ea08a1",
  "sync_started_at": "2026-04-24T16:55:36.974301+00:00"
}